{
  "School_DBExecuteSV_SubStr" : {
    "_id" : "wm-School_DBExecuteSV_SubStr-wm.ServiceVariable-1543998493546",
    "name" : "School_DBExecuteSV_SubStr",
    "owner" : "Page",
    "category" : "wm.ServiceVariable",
    "dataBinding" : [ ],
    "type" : "com.dbofflinestorage.school_db.models.query.SvSubStrResponse",
    "service" : "School_DB",
    "operation" : "executeSV_SubStr",
    "operationId" : "QueryExecutionController_executeSV_SubStr",
    "operationType" : "get",
    "serviceType" : "DataService",
    "dataSet" : [ ],
    "isList" : true,
    "maxResults" : 20,
    "startUpdate" : true,
    "autoUpdate" : true,
    "inFlightBehavior" : "executeLast",
    "transformationRequired" : false,
    "saveInPhonegap" : false,
    "isDefault" : true,
    "controller" : "QueryExecution"
  },
  "School_DBExecuteSV_SumFunction" : {
    "_id" : "wm-School_DBExecuteSV_SumFunction-wm.ServiceVariable-1543998558732",
    "name" : "School_DBExecuteSV_SumFunction",
    "owner" : "Page",
    "category" : "wm.ServiceVariable",
    "dataBinding" : [ {
      "target" : "ACADEMIC_YEAR",
      "value" : "2015-2016",
      "type" : "string"
    } ],
    "type" : "com.dbofflinestorage.school_db.models.query.SvSumFunctionResponse",
    "service" : "School_DB",
    "operation" : "executeSV_SumFunction",
    "operationId" : "QueryExecutionController_executeSV_SumFunction",
    "operationType" : "get",
    "serviceType" : "DataService",
    "dataSet" : [ ],
    "isList" : true,
    "maxResults" : 20,
    "startUpdate" : true,
    "autoUpdate" : true,
    "inFlightBehavior" : "executeLast",
    "transformationRequired" : false,
    "saveInPhonegap" : false,
    "isDefault" : true,
    "controller" : "QueryExecution"
  },
  "School_DBExecuteSV_UpperFunction" : {
    "_id" : "wm-School_DBExecuteSV_UpperFunction-wm.ServiceVariable-1543998630499",
    "name" : "School_DBExecuteSV_UpperFunction",
    "owner" : "Page",
    "category" : "wm.ServiceVariable",
    "dataBinding" : [ ],
    "type" : "com.dbofflinestorage.school_db.models.query.SvUpperFunctionResponse",
    "service" : "School_DB",
    "operation" : "executeSV_UpperFunction",
    "operationId" : "QueryExecutionController_executeSV_UpperFunction",
    "operationType" : "get",
    "serviceType" : "DataService",
    "dataSet" : [ ],
    "isList" : true,
    "maxResults" : 20,
    "startUpdate" : true,
    "autoUpdate" : true,
    "inFlightBehavior" : "executeLast",
    "transformationRequired" : false,
    "saveInPhonegap" : false,
    "isDefault" : true,
    "controller" : "QueryExecution"
  },
  "SV_MAXFunction" : {
    "_id" : "wm-SV_MAXFunction-wm.ServiceVariable-1543988784542",
    "name" : "SV_MAXFunction",
    "owner" : "Page",
    "category" : "wm.ServiceVariable",
    "dataBinding" : [ {
      "target" : "ACADEMIC_YEAR",
      "value" : "2015-2016",
      "type" : "string"
    } ],
    "type" : "com.dbofflinestorage.school_db.models.query.SvMaxfunctionResponse",
    "service" : "School_DB",
    "operation" : "executeSV_MAXFunction",
    "operationId" : "QueryExecutionController_executeSV_MAXFunction",
    "operationType" : "get",
    "serviceType" : "DataService",
    "dataSet" : [ ],
    "isList" : true,
    "maxResults" : 20,
    "startUpdate" : true,
    "autoUpdate" : true,
    "inFlightBehavior" : "executeLast",
    "transformationRequired" : false,
    "saveInPhonegap" : false,
    "controller" : "QueryExecution"
  }
}